namedtensor/__init__.py
namedtensor/core.py
namedtensor/distributions.py
namedtensor/schema.py
namedtensor/test_core.py
namedtensor/test_distributions.py
namedtensor/test_module.py
namedtensor/test_torch.py
namedtensor/test_wrap.py
namedtensor/torch_base.py
namedtensor/torch_helpers.py
namedtensor/torch_nn.py
namedtensor-0.0.2.dist-info/DESCRIPTION.rst
namedtensor-0.0.2.dist-info/METADATA
namedtensor-0.0.2.dist-info/RECORD
namedtensor-0.0.2.dist-info/WHEEL
namedtensor-0.0.2.dist-info/metadata.json
namedtensor-0.0.2.dist-info/top_level.txt
